Workbook

Sheet 概要
A1: カタログ広告 冬の入れ替え案（社内確認用）
A2: 作成 2026年10月18日 ／ 状態: 承認待ち（まだ広告には反映していません）
A4: なぜ入れ替えるのか
A5: Instagram・Facebook の「商品が並ぶ広告」（カタログ広告）に、いまも夏物が出ている。
A6: 9/26〜10/17 のカタログ広告費 76,544円のうち 63,776円（83%）が冬の新作以外に使われた（Wadi Pants・キャップ・自転車用バッグなど）。
A7: 直近7日のカタログ広告は広告1円あたりの売上 2.6円で、Meta 広告の中でいちばん低い。
A9: 何が変わるか（在庫ありの商品数。商品一覧シートから自動で数えます）
A10: 広告 | B10: 入れ替え前 | C10: 入れ替え後 | D10: うち新作 | E10: うち定番の冬物 | F10: 夏物を外しただけ | G10: 出なくなる
A11: HOUDINI | B11: =C11+G11-2 -> 155 | C11: =D11+E11+F11 -> 93 | D11: =COUNTIFS(商品一覧!$A$2:$A$724,$A11,商品一覧!$B$2:$B$724,"新作") -> 34 | E11: =COUNTIFS(商品一覧!$A$2:$A$724,$A11,商品一覧!$B$2:$B$724,"定番の冬物") -> 59 | F11: =COUNTIFS(商品一覧!$A$2:$A$724,$A11,商品一覧!$B$2:$B$724,"夏物を外しただけ") -> 0 | G11: =COUNTIFS(商品一覧!$A$2:$A$724,$A11,商品一覧!$B$2:$B$724,"出なくなる") -> 64
A12: ACLIMA | B12: =C12+G12-0 -> 144 | C12: =D12+E12+F12 -> 80 | D12: =COUNTIFS(商品一覧!$A$2:$A$724,$A12,商品一覧!$B$2:$B$724,"新作") -> 18 | E12: =COUNTIFS(商品一覧!$A$2:$A$724,$A12,商品一覧!$B$2:$B$724,"定番の冬物") -> 62 | F12: =COUNTIFS(商品一覧!$A$2:$A$724,$A12,商品一覧!$B$2:$B$724,"夏物を外しただけ") -> 0 | G12: =COUNTIFS(商品一覧!$A$2:$A$724,$A12,商品一覧!$B$2:$B$724,"出なくなる") -> 64
A13: POC | B13: =C13+G13-4 -> 154 | C13: =D13+E13+F13 -> 64 | D13: =COUNTIFS(商品一覧!$A$2:$A$724,$A13,商品一覧!$B$2:$B$724,"新作") -> 64 | E13: =COUNTIFS(商品一覧!$A$2:$A$724,$A13,商品一覧!$B$2:$B$724,"定番の冬物") -> 0 | F13: =COUNTIFS(商品一覧!$A$2:$A$724,$A13,商品一覧!$B$2:$B$724,"夏物を外しただけ") -> 0 | G13: =COUNTIFS(商品一覧!$A$2:$A$724,$A13,商品一覧!$B$2:$B$724,"出なくなる") -> 94
A14: NORRØNA 新作 | B14: 0 | C14: =D14+E14+F14 -> 19 | D14: =COUNTIFS(商品一覧!$A$2:$A$724,$A14,商品一覧!$B$2:$B$724,"新作") -> 19 | E14: =COUNTIFS(商品一覧!$A$2:$A$724,$A14,商品一覧!$B$2:$B$724,"定番の冬物") -> 0 | F14: =COUNTIFS(商品一覧!$A$2:$A$724,$A14,商品一覧!$B$2:$B$724,"夏物を外しただけ") -> 0 | G14: =COUNTIFS(商品一覧!$A$2:$A$724,$A14,商品一覧!$B$2:$B$724,"出なくなる") -> 0
A15: NORRØNA falketind | B15: =C15+G15-2 -> 46 | C15: =D15+E15+F15 -> 40 | D15: =COUNTIFS(商品一覧!$A$2:$A$724,$A15,商品一覧!$B$2:$B$724,"新作") -> 0 | E15: =COUNTIFS(商品一覧!$A$2:$A$724,$A15,商品一覧!$B$2:$B$724,"定番の冬物") -> 0 | F15: =COUNTIFS(商品一覧!$A$2:$A$724,$A15,商品一覧!$B$2:$B$724,"夏物を外しただけ") -> 40 | G15: =COUNTIFS(商品一覧!$A$2:$A$724,$A15,商品一覧!$B$2:$B$724,"出なくなる") -> 8
A16: NORRØNA femund | B16: =C16+G16-2 -> 35 | C16: =D16+E16+F16 -> 31 | D16: =COUNTIFS(商品一覧!$A$2:$A$724,$A16,商品一覧!$B$2:$B$724,"新作") -> 0 | E16: =COUNTIFS(商品一覧!$A$2:$A$724,$A16,商品一覧!$B$2:$B$724,"定番の冬物") -> 0 | F16: =COUNTIFS(商品一覧!$A$2:$A$724,$A16,商品一覧!$B$2:$B$724,"夏物を外しただけ") -> 31 | G16: =COUNTIFS(商品一覧!$A$2:$A$724,$A16,商品一覧!$B$2:$B$724,"出なくなる") -> 6
A17: NORRØNA lofoten | B17: =C17+G17-1 -> 21 | C17: =D17+E17+F17 -> 22 | D17: =COUNTIFS(商品一覧!$A$2:$A$724,$A17,商品一覧!$B$2:$B$724,"新作") -> 0 | E17: =COUNTIFS(商品一覧!$A$2:$A$724,$A17,商品一覧!$B$2:$B$724,"定番の冬物") -> 0 | F17: =COUNTIFS(商品一覧!$A$2:$A$724,$A17,商品一覧!$B$2:$B$724,"夏物を外しただけ") -> 22 | G17: =COUNTIFS(商品一覧!$A$2:$A$724,$A17,商品一覧!$B$2:$B$724,"出なくなる") -> 0
A18: NORRØNA trollveggen | B18: =C18+G18-2 -> 17 | C18: =D18+E18+F18 -> 19 | D18: =COUNTIFS(商品一覧!$A$2:$A$724,$A18,商品一覧!$B$2:$B$724,"新作") -> 0 | E18: =COUNTIFS(商品一覧!$A$2:$A$724,$A18,商品一覧!$B$2:$B$724,"定番の冬物") -> 0 | F18: =COUNTIFS(商品一覧!$A$2:$A$724,$A18,商品一覧!$B$2:$B$724,"夏物を外しただけ") -> 19 | G18: =COUNTIFS(商品一覧!$A$2:$A$724,$A18,商品一覧!$B$2:$B$724,"出なくなる") -> 0
A19: HESTRA | B19: =C19+G19-0 -> 119 | C19: =D19+E19+F19 -> 119 | D19: =COUNTIFS(商品一覧!$A$2:$A$724,$A19,商品一覧!$B$2:$B$724,"新作") -> 0 | E19: =COUNTIFS(商品一覧!$A$2:$A$724,$A19,商品一覧!$B$2:$B$724,"定番の冬物") -> 0 | F19: =COUNTIFS(商品一覧!$A$2:$A$724,$A19,商品一覧!$B$2:$B$724,"夏物を外しただけ") -> 119 | G19: =COUNTIFS(商品一覧!$A$2:$A$724,$A19,商品一覧!$B$2:$B$724,"出なくなる") -> 0
A20: 合計 | B20: =SUM(B11:B19) -> 691 | C20: =SUM(C11:C19) -> 487 | D20: =SUM(D11:D19) -> 135 | E20: =SUM(E11:E19) -> 121 | F20: =SUM(F11:F19) -> 231 | G20: =SUM(G11:G19) -> 236
A21: 入れ替え前 = いま広告に載っている在庫ありの商品数（新しく入荷して加わる商品の数を差し引いて計算）。
A22: 新作 = サイトの 2026FW 新作カテゴリ（POC はスノーカテゴリ）。定番の冬物 = 新作ではないが冬に売る商品（ダウン・中わた・フリース・ウールなど）。
A23: NORRØNA の各シリーズと HESTRA は、ショーツ・Tシャツ・スカートなどの夏物を外すだけ。
A24: NORRØNA 新作 は新しく作る広告で、NORRØNA senja（トレラン）の広告と置き換える。
A26: 変わらないこと
A27: ・1日の予算 7,000円
A28: ・見せる相手（全員向け）
A29: ・広告の文言「ブランド｜Fall / Winter 2026」
A30: ・アウトレット品は出さない
A32: 反映のしかた
A33: ・今の広告は止めずに、中の商品だけ入れ替える（審査なし）。
A34: ・NORRØNA 新作の広告だけ新しく作る（審査あり）。
... A48: 集計: Meta 広告（9/26〜10/17）、在庫・商品名・価格はサイトの商品フィード（作成日時点、税込）。作成: scripts/catalog_season_diff.py

Sheet 商品一覧
A1: 広告 | B1: 区分 | C1: 入れ替え後 | D1: 商品名 | E1: 価格（税込） | F1: 商品ID | G1: 商品ページ | H1: 確認 | I1: コメント
A2: HOUDINI | B2: 新作 | C2: 出る | D2: Ms Alpine Tech Houdi | E2: 49500 | F2: 1308100790 | G2: 開く
A3: HOUDINI | B3: 新作 | C3: 出る | D3: Ms Alpine Tech Pants | E3: 39600 | F3: 1308400960 | G3: 開く
A4: HOUDINI | B4: 新作 | C4: 出る | D4: Ms Core Tech Houdi | E4: 36300 | F4: 1308100830 | G4: 開く
A5: HOUDINI | B5: 新作 | C5: 出る | D5: Ms Core Tech Pants | E5: 28600 | F5: 1308600890 | G5: 開く
A6: HOUDINI | B6: 新作 | C6: 出る | D6: Ms Drop Knee Power Tights II | E6: 20900 | F6: 1308400910 | G6: 開く
A7: HOUDINI | B7: 新作 | C7: 出る | D7: Ms Liquid Chore Pants | E7: 25300 | F7: 1308600610 | G7: 開く
A8: HOUDINI | B8: 新作 | C8: 出る | D8: Ms Long Power Tights II | E8: 22000 | F8: 1308400890 | G8: 開く
A9: HOUDINI | B9: 新作 | C9: 出る | D9: Ms Lykan Full Zip | E9: 40700 | F9: 1308300750 | G9: 開く
A10: HOUDINI | B10: 新作 | C10: 出る | D10: Ms Lykan Vest | E10: 24200 | F10: 1308300730 | G10: 開く
A11: HOUDINI | B11: 新作 | C11: 出る | D11: Ms Moonwalk Houdi II | E11: 44000 | F11: 1308300850 | G11: 開く
A12: HOUDINI | B12: 新作 | C12: 出る | D12: Ms Nomad Tech Pants | E12: 37400 | F12: 1308600870 | G12: 開く
A13: HOUDINI | B13: 新作 | C13: 出る | D13: Ms Puremerino Crew | E13: 16500 | F13: 1308400810 | G13: 開く
... A724: HESTRA | B724: 夏物を外しただけ | C724: 出る | D724: 91881 HAND CUFF | E724: 1870 | F724: 1000918810 | G724: 開く
